echoscript/__init__.py
echoscript/audio2text.py
echoscript/cli.py
echoscript/gradio_app.py
echoscript/utils.py
echoscript-0.0.1.dist-info/LICENSE
echoscript-0.0.1.dist-info/METADATA
echoscript-0.0.1.dist-info/WHEEL
echoscript-0.0.1.dist-info/entry_points.txt
echoscript-0.0.1.dist-info/top_level.txt
echoscript-0.0.1.dist-info/RECORD
