Metadata-Version: 2.1
Name: echoscript
Version: 0.0.1
Summary: A audio-to-text conversion package
Author-email: Your Name <your.email@example.com>
Project-URL: Homepage, https://github.com/susuky/echoscript
Classifier: Intended Audience :: Developers
Classifier: License :: OSI Approved :: MIT License
Classifier: Programming Language :: Python :: 3
License-File: LICENSE
Provides-Extra: test
Requires-Dist: pytest; extra == "test"
Requires-Dist: coverage; extra == "test"
